{
  "timestamp": "2026-05-30T16:51:39.903621+00:00",
  "azure": {
    "serviceName": "Azure",
    "mtdTotal": 0,
    "lastMonth": 0,
    "dailyAvg": 0.0,
    "eomForecast": 0.0,
    "resources": [],
    "spikeDetected": false,
    "spikePct": 0,
    "analysis": "Spending is $0 MTD, trending to $0 by month-end."
  },
  "elevenlabs": {
    "planName": "Enterprise",
    "status": "Active",
    "percentUsed": 7.2,
    "charsUsed": 21642061,
    "charLimit": 300000000,
    "charsRemaining": 278357939,
    "burnRatePerDay": 21642061.0,
    "projectedEOM": 627619769.0,
    "willExceed": true,
    "daysToReset": 29,
    "daysToExhaustion": 12,
    "voiceSlots": {
      "standard": {
        "used": 0,
        "limit": 20000
      },
      "professional": {
        "used": 0,
        "limit": 10
      }
    },
    "analysis": "\u26a0\ufe0f Will exceed limit in ~12 days"
  }
}